setup.py
sqltocache/__init__.py
sqltocache/cacheToRedis.py
sqltocache.egg-info/PKG-INFO
sqltocache.egg-info/SOURCES.txt
sqltocache.egg-info/dependency_links.txt
sqltocache.egg-info/requires.txt
sqltocache.egg-info/top_level.txt