Metadata-Version: 1.0
Name: sqltocache
Version: 1.0
Summary: result of sql cache to redis
Home-page: https://github.com/rfyiamcool
Author: fengyun.rui
Author-email: rfyiamcool@163.com
License: UNKNOWN
Platform: UNKNOWN
